jflatdb/__init__.py
jflatdb/cli.py
jflatdb/database.py
jflatdb/indexer.py
jflatdb/query_engine.py
jflatdb/schema.py
jflatdb/security.py
jflatdb/storage.py
jflatdb/utils/__init__.py
jflatdb/utils/helpers.py
jflatdb/utils/logger.py
jflatdb-0.0.3.dist-info/licenses/LICENSE
jflatdb-0.0.3.dist-info/METADATA
jflatdb-0.0.3.dist-info/WHEEL
jflatdb-0.0.3.dist-info/entry_points.txt
jflatdb-0.0.3.dist-info/top_level.txt
jflatdb-0.0.3.dist-info/RECORD
