Metadata-Version: 2.4
Name: jflatdb
Version: 0.0.3
Summary: A lightweight JSON-based flat file database system.
Home-page: https://github.com/jflatdb/jflatdb
Author: Akki
Author-email: akki.jflatdb@gmail.com
License: MIT
Classifier: Programming Language :: Python :: 3
Classifier: License :: OSI Approved :: MIT License
Classifier: Operating System :: OS Independent
Requires-Python: >=3.7
License-File: LICENSE
Dynamic: author
Dynamic: author-email
Dynamic: classifier
Dynamic: description
Dynamic: description-content-type
Dynamic: home-page
Dynamic: license
Dynamic: license-file
Dynamic: requires-python
Dynamic: summary
